{"jobJson":{"DSJobDef":{"ParameterFileDDName":"DD00001","TransactionSize":"0","_xmeta_repos_object_id":"c2e76d84.43058877.jb96o1sfo.229lbol.90oeqd.e85vmvg1jd0jo43nsljff","DSNameSpace":"NYIIS117:Project3","ExpressionSemanticCheckFlag":"0","NextID":"1","Container":"V0","EnableCacheSharing":"false","DSDesignView":{"_xmeta_optimistic_lock_id":"1","_xmeta_creation_timestamp":"2019-07-19T00:09:17+0000","InternalID":"V0","_xmeta_modified_by_user":"isadmin","ContainerViewSizing":"0000 0000 1137 0620 0000 0000 0000 0000","NextStageID":"7","StageXSize":"48|48|48","_xmeta_lockingRoot":"c2e76d84.43058877.jb96o1sfo.229lbol.90oeqd.e85vmvg1jd0jo43nsljff","StageYPos":"216|216|216","StageXPos":"192|360|504","_xmeta_repos_object_id":"c2e76d84.c6671f72.jb96o1sfo.21p48it.qe4g0c.vptrro98sp7ue9uahinsa","StageTypes":"CCustomStage.CC_GUI|CTransformerStage|CCustomStage.CC_GUI","GridLines":"0","NextID":"1","isSystem":"false","StageYSize":"48|48|48","ZoomValue":"100","SnapToGrid":"1","StageList":"V0S0|V0S3|V0S6","_xmeta_modification_timestamp":"2019-07-19T00:09:17+0000","name":"Job","_xmeta_created_by_user":"isadmin","IsTopLevel":"false","LazyLoadInfo":"StageID=V0S0|StageNames=SAM115_T|StageTypeIDs=DB2ConnectorPX|LI=OutputPinID=V0S0P1|LI=LinkHasMetaDatas=1|LI=LinkNamePositionXs=302|LI=LinkNamePositionYs=236|LI=LinkNames=DSLink2|LI=LinkTypes=1|LI=TargetStageIDs=V0S3|LI=SourceStageEffectiveExecutionModes=2|LI=SourceStageRuntimeExecutionModes=2|LI=TargetStageEffectiveExecutionModes=2|LI=TargetStageRuntimeExecutionModes=2|LI=LinkIsSingleOperatorLookup=0|LI=LinkIsSortSequential=0|LI=LinkPartColMode=1|LI=LinkSortMode=0\u00a0StageID=V0S3|StageNames=Transformer_3|StageTypeIDs=CTransformerStage|LI=OutputPinID=V0S3P2|LI=LinkHasMetaDatas=1|LI=LinkNamePositionXs=457|LI=LinkNamePositionYs=239|LI=LinkNames=DSLink5|LI=LinkTypes=1|LI=TargetStageIDs=V0S6|LI=SourceStageEffectiveExecutionModes=2|LI=SourceStageRuntimeExecutionModes=2|LI=TargetStageEffectiveExecutionModes=2|LI=TargetStageRuntimeExecutionModes=2|LI=LinkIsSingleOperatorLookup=0|LI=LinkIsSortSequential=0|LI=LinkPartColMode=1|LI=LinkSortMode=0\u00a0StageID=V0S6|StageNames=SAM_T|StageTypeIDs=DB2ConnectorPX|"},"DSLink":[{"_xmeta_optimistic_lock_id":"1","from_OutputPin":"c2e76d84.b9af3d05.jb96o1sfo.229nqu3.notale.7tmeo8b1hq1kk5evgr9dg","_xmeta_creation_timestamp":"2019-07-19T00:09:17+0000","_xmeta_modified_by_user":"isadmin","DSFlowVariable":[{"_xmeta_optimistic_lock_id":"2","Group":"0","_xmeta_modified_by_user":"isadmin","isSigned":"true","AllowCRLF":"0","minimumLength":"0","_xmeta_lockingRoot":"c2e76d84.43058877.jb96o1sfo.229lbol.90oeqd.e85vmvg1jd0jo43nsljff","SortKey":"0","_xmeta_repos_object_id":"c2e76d84.cf7a27f9.jb96o1sfo.229ltvq.30glg5.o7pqqkf5rllenig5cbq1v","displaySize":"0","IsKey":"false","maximumLength":"0","_xmeta_modification_timestamp":"2019-07-19T00:09:18+0000","levelNumber":"0","PadNulls":"0","PKeyIsCaseless":"0","SortingOrder":"0","ArrayHandling":"0","_xmeta_creation_timestamp":"2019-07-19T00:09:17+0000","isSourceOf_FlowVariable":["c2e76d84.cf7a27f9.jb96o1sfo.nejl0fp.bu2ise.pg1kkilg8m2d8me1o4c18"],"fractionDigits":"0","IsUString":"false","ODBCType":"INTEGER","typeCode":"INT32","SortType":"0","isNullable":"false","name":"COL1","_xmeta_created_by_user":"isadmin"}],"StageInfo":"SAM115_T=DB2ConnectorPX=CustomStage","_xmeta_lockingRoot":"c2e76d84.43058877.jb96o1sfo.229lbol.90oeqd.e85vmvg1jd0jo43nsljff","to_InputPin":"c2e76d84.159ac31a.jb96o1sfo.229kqt5.ci1f13.3muksq9dtr3rjphj7vjaf","_xmeta_repos_object_id":"c2e76d84.78bf4d29.jb96o1sfo.229bdl1.43gu86.79tugavfgp3gcus9je1d9","isSystem":"false","_xmeta_modification_timestamp":"2019-07-19T00:09:17+0000","name":"DSLink2","DSParameterVal":[{"_xmeta_optimistic_lock_id":"1","_xmeta_creation_timestamp":"2019-07-19T00:09:17+0000","valueExpression":"0","_xmeta_modified_by_user":"isadmin","_xmeta_lockingRoot":"c2e76d84.43058877.jb96o1sfo.229lbol.90oeqd.e85vmvg1jd0jo43nsljff","usage":"OUT","_xmeta_modification_timestamp":"2019-07-19T00:09:17+0000","_xmeta_created_by_user":"isadmin","parameterName":"LinkMinimised","_xmeta_repos_object_id":"c2e76d84.19e8ce7.jb96o1sfo.229m3js.4edsjn.pgcpnr090ml0okvg9n83vd","ParamType":"DIRECT"},{"_xmeta_optimistic_lock_id":"1","_xmeta_creation_timestamp":"2019-07-19T00:09:17+0000","valueExpression":"0","_xmeta_modified_by_user":"isadmin","_xmeta_lockingRoot":"c2e76d84.43058877.jb96o1sfo.229lbol.90oeqd.e85vmvg1jd0jo43nsljff","usage":"OUT","_xmeta_modification_timestamp":"2019-07-19T00:09:17+0000","_xmeta_created_by_user":"isadmin","parameterName":"RejectNumber","_xmeta_repos_object_id":"c2e76d84.19e8ce7.jb96o1sfo.229apm8.sfm54e.evutdbsn5ddgc5q3vvpvhd","ParamType":"DIRECT"},{"_xmeta_optimistic_lock_id":"1","_xmeta_creation_timestamp":"2019-07-19T00:09:17+0000","valueExpression":"false","_xmeta_modified_by_user":"isadmin","_xmeta_lockingRoot":"c2e76d84.43058877.jb96o1sfo.229lbol.90oeqd.e85vmvg1jd0jo43nsljff","usage":"OUT","_xmeta_modification_timestamp":"2019-07-19T00:09:17+0000","_xmeta_created_by_user":"isadmin","parameterName":"RejectUsesPercentage","_xmeta_repos_object_id":"c2e76d84.19e8ce7.jb96o1sfo.21p6mem.iropqa.8n8kd4ac0jvl7j2ep6agmd","ParamType":"DIRECT"},{"_xmeta_optimistic_lock_id":"1","_xmeta_creation_timestamp":"2019-07-19T00:09:17+0000","valueExpression":"-1","_xmeta_modified_by_user":"isadmin","_xmeta_lockingRoot":"c2e76d84.43058877.jb96o1sfo.229lbol.90oeqd.e85vmvg1jd0jo43nsljff","usage":"OUT","_xmeta_modification_timestamp":"2019-07-19T00:09:17+0000","_xmeta_created_by_user":"isadmin","parameterName":"RejectFromLink","_xmeta_repos_object_id":"c2e76d84.19e8ce7.jb96o1sfo.229cbul.gofmp5.rs134082q6g9n361s3enpd","ParamType":"DIRECT"},{"_xmeta_optimistic_lock_id":"1","_xmeta_creation_timestamp":"2019-07-19T00:09:17+0000","valueExpression":"1.0","_xmeta_modified_by_user":"isadmin","_xmeta_lockingRoot":"c2e76d84.43058877.jb96o1sfo.229lbol.90oeqd.e85vmvg1jd0jo43nsljff","usage":"OUT","_xmeta_modification_timestamp":"2019-07-19T00:09:17+0000","_xmeta_created_by_user":"isadmin","parameterName":"VariantVersion","_xmeta_repos_object_id":"c2e76d84.19e8ce7.jb96o1sfo.21p69q3.11ir1s.uiknd81r2ui9fjc2o6c96d","ParamType":"DIRECT"},{"_xmeta_optimistic_lock_id":"1","_xmeta_creation_timestamp":"2019-07-19T00:09:17+0000","_xmeta_modified_by_user":"isadmin","_xmeta_lockingRoot":"c2e76d84.43058877.jb96o1sfo.229lbol.90oeqd.e85vmvg1jd0jo43nsljff","usage":"OUT","_xmeta_modification_timestamp":"2019-07-19T00:09:17+0000","_xmeta_created_by_user":"isadmin","parameterName":"lookup\\\\type","_xmeta_repos_object_id":"c2e76d84.19e8ce7.jb96o1sfo.229e1h7.8kd2e0.4v5o6tputdfj3lr4pji1ld","ParamType":"DIRECT"},{"_xmeta_optimistic_lock_id":"1","_xmeta_creation_timestamp":"2019-07-19T00:09:17+0000","valueExpression":"ccdb2","_xmeta_modified_by_user":"isadmin","_xmeta_lockingRoot":"c2e76d84.43058877.jb96o1sfo.229lbol.90oeqd.e85vmvg1jd0jo43nsljff","usage":"OUT","_xmeta_modification_timestamp":"2019-07-19T00:09:17+0000","_xmeta_created_by_user":"isadmin","parameterName":"VariantLibrary","_xmeta_repos_object_id":"c2e76d84.19e8ce7.jb96o1sfo.21p1ejc.kald6e.djllro97li2rvgd9jise2d","ParamType":"DIRECT"},{"_xmeta_optimistic_lock_id":"1","_xmeta_creation_timestamp":"2019-07-19T00:09:17+0000","valueExpression":"9.1","_xmeta_modified_by_user":"isadmin","_xmeta_lockingRoot":"c2e76d84.43058877.jb96o1sfo.229lbol.90oeqd.e85vmvg1jd0jo43nsljff","usage":"OUT","_xmeta_modification_timestamp":"2019-07-19T00:09:17+0000","_xmeta_created_by_user":"isadmin","parameterName":"VariantName","_xmeta_repos_object_id":"c2e76d84.19e8ce7.jb96o1sfo.229kkqb.ogkqde.h41a24gicrbbqo2bvhfgfd","ParamType":"DIRECT"},{"_xmeta_optimistic_lock_id":"1","_xmeta_creation_timestamp":"2019-07-19T00:09:17+0000","valueExpression":"0","_xmeta_modified_by_user":"isadmin","_xmeta_lockingRoot":"c2e76d84.43058877.jb96o1sfo.229lbol.90oeqd.e85vmvg1jd0jo43nsljff","usage":"OUT","_xmeta_modification_timestamp":"2019-07-19T00:09:17+0000","_xmeta_created_by_user":"isadmin","parameterName":"RejectThreshold","_xmeta_repos_object_id":"c2e76d84.19e8ce7.jb96o1sfo.229j1ia.4kv37s.s5jrbrlkn6r40j00ja67rd","ParamType":"DIRECT"},{"_xmeta_optimistic_lock_id":"1","_xmeta_creation_timestamp":"2019-07-19T00:09:17+0000","valueExpression":"DB2Connector","_xmeta_modified_by_user":"isadmin","_xmeta_lockingRoot":"c2e76d84.43058877.jb96o1sfo.229lbol.90oeqd.e85vmvg1jd0jo43nsljff","usage":"OUT","_xmeta_modification_timestamp":"2019-07-19T00:09:17+0000","_xmeta_created_by_user":"isadmin","parameterName":"ConnectorName","_xmeta_repos_object_id":"c2e76d84.19e8ce7.jb96o1sfo.229jpm7.g04lic.rdsuk4u8ap3p2gcvl8qv7d","ParamType":"DIRECT"},{"_xmeta_optimistic_lock_id":"1","_xmeta_creation_timestamp":"2019-07-19T00:09:17+0000","valueExpression":"0","_xmeta_modified_by_user":"isadmin","_xmeta_lockingRoot":"c2e76d84.43058877.jb96o1sfo.229lbol.90oeqd.e85vmvg1jd0jo43nsljff","usage":"IN","_xmeta_modification_timestamp":"2019-07-19T00:09:17+0000","_xmeta_created_by_user":"isadmin","parameterName":"LinkMinimised","_xmeta_repos_object_id":"c2e76d84.19e8ce7.jb96o1sfo.229hhi0.bk9fli.ucus0onktikksolv855rjd","ParamType":"DIRECT"},{"_xmeta_optimistic_lock_id":"1","_xmeta_creation_timestamp":"2019-07-19T00:09:17+0000","valueExpression":"0","_xmeta_modified_by_user":"isadmin","_xmeta_lockingRoot":"c2e76d84.43058877.jb96o1sfo.229lbol.90oeqd.e85vmvg1jd0jo43nsljff","usage":"IN","_xmeta_modification_timestamp":"2019-07-19T00:09:17+0000","_xmeta_created_by_user":"isadmin","parameterName":"MultiRow","_xmeta_repos_object_id":"c2e76d84.19e8ce7.jb96o1sfo.229gpuq.qqoukm.on0rv16joqa4atfskfkr3d","ParamType":"DIRECT"}],"linkType":"PRIMARY","_xmeta_created_by_user":"isadmin"},{"_xmeta_optimistic_lock_id":"2","from_OutputPin":"c2e76d84.b9af3d05.jb96o1sfo.229b5d3.srdpgd.mn2epm7csnuv2b3ntiem9","_xmeta_creation_timestamp":"2019-07-19T00:09:17+0000","_xmeta_modified_by_user":"isadmin","DSFlowVariable":[{"_xmeta_optimistic_lock_id":"1","Group":"0","_xmeta_modified_by_user":"isadmin","isSigned":"true","AllowCRLF":"0","minimumLength":"0","_xmeta_lockingRoot":"c2e76d84.43058877.jb96o1sfo.229lbol.90oeqd.e85vmvg1jd0jo43nsljff","SortKey":"0","_xmeta_repos_object_id":"c2e76d84.cf7a27f9.jb96o1sfo.nejl0fp.bu2ise.pg1kkilg8m2d8me1o4c18","displaySize":"0","IsKey":"false","maximumLength":"0","_xmeta_modification_timestamp":"2019-07-19T00:09:18+0000","levelNumber":"0","PadNulls":"0","PKeyIsCaseless":"0","SortingOrder":"0","ArrayHandling":"0","_xmeta_creation_timestamp":"2019-07-19T00:09:18+0000","hasValue_Derivation":[{"_xmeta_optimistic_lock_id":"1","_xmeta_creation_timestamp":"2019-07-19T00:09:18+0000","_xmeta_modified_by_user":"isadmin","expression":"DSLink2.COL1 + 20","_xmeta_lockingRoot":"c2e76d84.43058877.jb96o1sfo.229lbol.90oeqd.e85vmvg1jd0jo43nsljff","_xmeta_modification_timestamp":"2019-07-19T00:09:18+0000","ParsedExpression":"DSLink2.COL1 + 20","SourceColumn":"DSLink2.COL1","name":"","_xmeta_created_by_user":"isadmin","_xmeta_repos_object_id":"c2e76d84.777516a6.jb96o1sfo.ng5o3hl.t20807.gs3l6l57faf1s0hb95ub8"}],"fractionDigits":"0","IsUString":"false","ODBCType":"INTEGER","typeCode":"INT32","SortType":"0","hasSource_FlowVariable":["c2e76d84.cf7a27f9.jb96o1sfo.229ltvq.30glg5.o7pqqkf5rllenig5cbq1v"],"isNullable":"false","name":"COL1","_xmeta_created_by_user":"isadmin"}],"StageInfo":"Transformer_3=CTransformerStage=TransformerStage","_xmeta_lockingRoot":"c2e76d84.43058877.jb96o1sfo.229lbol.90oeqd.e85vmvg1jd0jo43nsljff","to_InputPin":"c2e76d84.159ac31a.jb96o1sfo.229i6m9.omj8uq.hsarsrnevovrtcj6f4l1b","_xmeta_repos_object_id":"c2e76d84.78bf4d29.jb96o1sfo.21p6gt4.8go02d.h90paosthfq38ge81u076","isSystem":"false","_xmeta_modification_timestamp":"2019-07-19T00:09:18+0000","name":"DSLink5","DSParameterVal":[{"_xmeta_optimistic_lock_id":"1","_xmeta_creation_timestamp":"2019-07-19T00:09:17+0000","valueExpression":"0","_xmeta_modified_by_user":"isadmin","_xmeta_lockingRoot":"c2e76d84.43058877.jb96o1sfo.229lbol.90oeqd.e85vmvg1jd0jo43nsljff","usage":"OUT","_xmeta_modification_timestamp":"2019-07-19T00:09:17+0000","_xmeta_created_by_user":"isadmin","parameterName":"ErrorPin","_xmeta_repos_object_id":"c2e76d84.19e8ce7.jb96o1sfo.21p5c22.h47uca.43klessavqmk7cq9chdiqd","ParamType":"DIRECT"},{"_xmeta_optimistic_lock_id":"1","_xmeta_creation_timestamp":"2019-07-19T00:09:17+0000","valueExpression":"0","_xmeta_modified_by_user":"isadmin","_xmeta_lockingRoot":"c2e76d84.43058877.jb96o1sfo.229lbol.90oeqd.e85vmvg1jd0jo43nsljff","usage":"OUT","_xmeta_modification_timestamp":"2019-07-19T00:09:17+0000","_xmeta_created_by_user":"isadmin","parameterName":"Reject","_xmeta_repos_object_id":"c2e76d84.19e8ce7.jb96o1sfo.229k5d4.8biub1.g9ikkg8usvaagaoh2tfend","ParamType":"DIRECT"},{"_xmeta_optimistic_lock_id":"1","_xmeta_creation_timestamp":"2019-07-19T00:09:17+0000","valueExpression":"0","_xmeta_modified_by_user":"isadmin","_xmeta_lockingRoot":"c2e76d84.43058877.jb96o1sfo.229lbol.90oeqd.e85vmvg1jd0jo43nsljff","usage":"OUT","_xmeta_modification_timestamp":"2019-07-19T00:09:17+0000","_xmeta_created_by_user":"isadmin","parameterName":"LinkMinimised","_xmeta_repos_object_id":"c2e76d84.19e8ce7.jb96o1sfo.21p8287.u0f0d2.ljgpa2iugq0qecif5pired","ParamType":"DIRECT"},{"_xmeta_optimistic_lock_id":"1","_xmeta_creation_timestamp":"2019-07-19T00:09:17+0000","valueExpression":"0","_xmeta_modified_by_user":"isadmin","_xmeta_lockingRoot":"c2e76d84.43058877.jb96o1sfo.229lbol.90oeqd.e85vmvg1jd0jo43nsljff","usage":"OUT","_xmeta_modification_timestamp":"2019-07-19T00:09:17+0000","_xmeta_created_by_user":"isadmin","parameterName":"RowLimit","_xmeta_repos_object_id":"c2e76d84.19e8ce7.jb96o1sfo.21p7piv.kaf5qb.e16eu36q8jav4vmj7jaded","ParamType":"DIRECT"},{"_xmeta_optimistic_lock_id":"1","_xmeta_creation_timestamp":"2019-07-19T00:09:17+0000","valueExpression":"0","_xmeta_modified_by_user":"isadmin","_xmeta_lockingRoot":"c2e76d84.43058877.jb96o1sfo.229lbol.90oeqd.e85vmvg1jd0jo43nsljff","usage":"IN","_xmeta_modification_timestamp":"2019-07-19T00:09:17+0000","_xmeta_created_by_user":"isadmin","parameterName":"LinkMinimised","_xmeta_repos_object_id":"c2e76d84.19e8ce7.jb96o1sfo.21p87un.0iat9i.m41gdanlrm6p544pdpf8ud","ParamType":"DIRECT"},{"_xmeta_optimistic_lock_id":"1","_xmeta_creation_timestamp":"2019-07-19T00:09:17+0000","valueExpression":"0","_xmeta_modified_by_user":"isadmin","_xmeta_lockingRoot":"c2e76d84.43058877.jb96o1sfo.229lbol.90oeqd.e85vmvg1jd0jo43nsljff","usage":"IN","_xmeta_modification_timestamp":"2019-07-19T00:09:17+0000","_xmeta_created_by_user":"isadmin","parameterName":"RejectNumber","_xmeta_repos_object_id":"c2e76d84.19e8ce7.jb96o1sfo.229dnro.b6pcs0.dsafa8hplv63ingmlvfild","ParamType":"DIRECT"},{"_xmeta_optimistic_lock_id":"1","_xmeta_creation_timestamp":"2019-07-19T00:09:17+0000","valueExpression":"false","_xmeta_modified_by_user":"isadmin","_xmeta_lockingRoot":"c2e76d84.43058877.jb96o1sfo.229lbol.90oeqd.e85vmvg1jd0jo43nsljff","usage":"IN","_xmeta_modification_timestamp":"2019-07-19T00:09:17+0000","_xmeta_created_by_user":"isadmin","parameterName":"RejectUsesPercentage","_xmeta_repos_object_id":"c2e76d84.19e8ce7.jb96o1sfo.21p2d6j.fsg4p1.b63h8kf0mt0vgtq154o92d","ParamType":"DIRECT"},{"_xmeta_optimistic_lock_id":"1","_xmeta_creation_timestamp":"2019-07-19T00:09:17+0000","valueExpression":"-1","_xmeta_modified_by_user":"isadmin","_xmeta_lockingRoot":"c2e76d84.43058877.jb96o1sfo.229lbol.90oeqd.e85vmvg1jd0jo43nsljff","usage":"IN","_xmeta_modification_timestamp":"2019-07-19T00:09:17+0000","_xmeta_created_by_user":"isadmin","parameterName":"RejectFromLink","_xmeta_repos_object_id":"c2e76d84.19e8ce7.jb96o1sfo.21p9h3m.eknac5.cmn6vp4f33iojfp496761d","ParamType":"DIRECT"},{"_xmeta_optimistic_lock_id":"1","_xmeta_creation_timestamp":"2019-07-19T00:09:17+0000","valueExpression":"1.0","_xmeta_modified_by_user":"isadmin","_xmeta_lockingRoot":"c2e76d84.43058877.jb96o1sfo.229lbol.90oeqd.e85vmvg1jd0jo43nsljff","usage":"IN","_xmeta_modification_timestamp":"2019-07-19T00:09:17+0000","_xmeta_created_by_user":"isadmin","parameterName":"VariantVersion","_xmeta_repos_object_id":"c2e76d84.19e8ce7.jb96o1sfo.229ngm7.rqd08l.9k8pgcssjr9sugddmhd0gt","ParamType":"DIRECT"},{"_xmeta_optimistic_lock_id":"1","_xmeta_creation_timestamp":"2019-07-19T00:09:17+0000","valueExpression":"ccdb2","_xmeta_modified_by_user":"isadmin","_xmeta_lockingRoot":"c2e76d84.43058877.jb96o1sfo.229lbol.90oeqd.e85vmvg1jd0jo43nsljff","usage":"IN","_xmeta_modification_timestamp":"2019-07-19T00:09:17+0000","_xmeta_created_by_user":"isadmin","parameterName":"VariantLibrary","_xmeta_repos_object_id":"c2e76d84.19e8ce7.jb96o1sfo.229a4cp.6ohe8p.vsq52f4hr7lq698ungb31d","ParamType":"DIRECT"},{"_xmeta_optimistic_lock_id":"1","_xmeta_creation_timestamp":"2019-07-19T00:09:17+0000","valueExpression":"9.1","_xmeta_modified_by_user":"isadmin","_xmeta_lockingRoot":"c2e76d84.43058877.jb96o1sfo.229lbol.90oeqd.e85vmvg1jd0jo43nsljff","usage":"IN","_xmeta_modification_timestamp":"2019-07-19T00:09:17+0000","_xmeta_created_by_user":"isadmin","parameterName":"VariantName","_xmeta_repos_object_id":"c2e76d84.19e8ce7.jb96o1sfo.229ic0s.05p1tb.pn4ace32pccgk2gmrmvnbd","ParamType":"DIRECT"},{"_xmeta_optimistic_lock_id":"1","_xmeta_creation_timestamp":"2019-07-19T00:09:17+0000","valueExpression":"0","_xmeta_modified_by_user":"isadmin","_xmeta_lockingRoot":"c2e76d84.43058877.jb96o1sfo.229lbol.90oeqd.e85vmvg1jd0jo43nsljff","usage":"IN","_xmeta_modification_timestamp":"2019-07-19T00:09:17+0000","_xmeta_created_by_user":"isadmin","parameterName":"RejectThreshold","_xmeta_repos_object_id":"c2e76d84.19e8ce7.jb96o1sfo.21p3m0m.0kmsuc.9p32clhjcbhj65u6m8teid","ParamType":"DIRECT"},{"_xmeta_optimistic_lock_id":"1","_xmeta_creation_timestamp":"2019-07-19T00:09:17+0000","valueExpression":"DB2Connector","_xmeta_modified_by_user":"isadmin","_xmeta_lockingRoot":"c2e76d84.43058877.jb96o1sfo.229lbol.90oeqd.e85vmvg1jd0jo43nsljff","usage":"IN","_xmeta_modification_timestamp":"2019-07-19T00:09:17+0000","_xmeta_created_by_user":"isadmin","parameterName":"ConnectorName","_xmeta_repos_object_id":"c2e76d84.19e8ce7.jb96o1sfo.229a9ku.nvpp1h.ihcpstlho3lcin1jci20hd","ParamType":"DIRECT"}],"linkType":"PRIMARY","_xmeta_created_by_user":"isadmin"}],"_xmeta_modification_timestamp":"2019-07-19T00:09:18+0000","IMSProgType":"0","ControlAfterSubr":"false","IsTemplate":"false","Uploadable":"false","_xmeta_creation_timestamp":"2019-07-19T00:09:17+0000","NextAliasID":"2","Act2ActBufferSize":"0","ReservedWordCheck":"1","RuntimeColumnPropagation":"false","version":"56.0.0","isSystem":"false","name":"T_Lineage","WebServiceEnabled":"false","_xmeta_created_by_user":"isadmin","AllowMultipleInvocations":"false","DSJobType":"3","CopyLibPrefix":"ARDT","TraceOption":"0","Act2ActIPCTimeout":"0","DSStage":[{"_xmeta_optimistic_lock_id":"2","StageTypeClassName":"CustomStage","_xmeta_creation_timestamp":"2019-07-19T00:09:17+0000","InternalID":"V0S0","_xmeta_modified_by_user":"isadmin","_xmeta_lockingRoot":"c2e76d84.43058877.jb96o1sfo.229lbol.90oeqd.e85vmvg1jd0jo43nsljff","DSOutputPin":[{"_xmeta_optimistic_lock_id":"1","LeftTextPos":"302","_xmeta_creation_timestamp":"2019-07-19T00:09:17+0000","InternalID":"V0S0P1","_xmeta_modified_by_user":"isadmin","_xmeta_lockingRoot":"c2e76d84.43058877.jb96o1sfo.229lbol.90oeqd.e85vmvg1jd0jo43nsljff","_xmeta_repos_object_id":"c2e76d84.b9af3d05.jb96o1sfo.229nqu3.notale.7tmeo8b1hq1kk5evgr9dg","TopTextPos":"236","DSMetaBag":{"_xmeta_optimistic_lock_id":"1","Names":"DiskWriteInc\u00a0BufFreeRun\u00a0MaxMemBufSize\u00a0QueueUpperSize","_xmeta_creation_timestamp":"2019-07-19T00:09:17+0000","_xmeta_modified_by_user":"isadmin","_xmeta_lockingRoot":"c2e76d84.43058877.jb96o1sfo.229lbol.90oeqd.e85vmvg1jd0jo43nsljff","_xmeta_modification_timestamp":"2019-07-19T00:09:17+0000","Values":"1048576\u00a050\u00a03145728\u00a00","_xmeta_created_by_user":"isadmin","_xmeta_repos_object_id":"c2e76d84.ac581434.jb96o1sfo.229fgm5.589tup.r4ttpgmp8odup9q96fast","Conditions":"\u00a0\u00a0\u00a0","Owners":"APT\u00a0APT\u00a0APT\u00a0APT"},"_xmeta_modification_timestamp":"2019-07-19T00:09:17+0000","PinType":"CustomOutput","_xmeta_created_by_user":"isadmin","Partner":"V0S3|V0S3P1","isSourceOf_Link":"c2e76d84.78bf4d29.jb96o1sfo.229bdl1.43gu86.79tugavfgp3gcus9je1d9"}],"_xmeta_repos_object_id":"c2e76d84.9f91cbaf.jb96o1sfo.21p4231.nue8ib.uicaluudmj2ged3g4ncbi","NextID":"2","AllowColumnMapping":"false","isSystem":"false","StageType":"DB2ConnectorPX","_xmeta_modification_timestamp":"2019-07-19T00:09:18+0000","name":"SAM115_T","DSParameterVal":[{"_xmeta_optimistic_lock_id":"1","_xmeta_creation_timestamp":"2019-07-19T00:09:17+0000","valueExpression":"\/Connection\/Conductor\/Username","_xmeta_modified_by_user":"isadmin","_xmeta_lockingRoot":"c2e76d84.43058877.jb96o1sfo.229lbol.90oeqd.e85vmvg1jd0jo43nsljff","usage":"DEFAULT","_xmeta_modification_timestamp":"2019-07-19T00:09:17+0000","_xmeta_created_by_user":"isadmin","parameterName":"ConductorUsername","_xmeta_repos_object_id":"c2e76d84.19e8ce7.jb96o1sfo.229ei0m.cn6iid.bp6jp9c1crc8gjc3gq28dd","ParamType":"DIRECT"},{"_xmeta_optimistic_lock_id":"1","_xmeta_creation_timestamp":"2019-07-19T00:09:17+0000","valueExpression":"\/Connection\/Conductor\/Instance","_xmeta_modified_by_user":"isadmin","_xmeta_lockingRoot":"c2e76d84.43058877.jb96o1sfo.229lbol.90oeqd.e85vmvg1jd0jo43nsljff","usage":"DEFAULT","_xmeta_modification_timestamp":"2019-07-19T00:09:17+0000","_xmeta_created_by_user":"isadmin","parameterName":"ConductorInstance","_xmeta_repos_object_id":"c2e76d84.19e8ce7.jb96o1sfo.21p3g1h.9o6jnc.1ldg7is6jpkmp01g8jt4id","ParamType":"DIRECT"},{"_xmeta_optimistic_lock_id":"1","_xmeta_creation_timestamp":"2019-07-19T00:09:17+0000","valueExpression":"\/Connection\/Instance","_xmeta_modified_by_user":"isadmin","_xmeta_lockingRoot":"c2e76d84.43058877.jb96o1sfo.229lbol.90oeqd.e85vmvg1jd0jo43nsljff","usage":"DEFAULT","_xmeta_modification_timestamp":"2019-07-19T00:09:17+0000","_xmeta_created_by_user":"isadmin","parameterName":"Instance","_xmeta_repos_object_id":"c2e76d84.19e8ce7.jb96o1sfo.229g0o3.5mo992.u64aijdg5ftqbea4vlkvtd","ParamType":"DIRECT"},{"_xmeta_optimistic_lock_id":"1","_xmeta_creation_timestamp":"2019-07-19T00:09:17+0000","valueExpression":"ccdb2","_xmeta_modified_by_user":"isadmin","_xmeta_lockingRoot":"c2e76d84.43058877.jb96o1sfo.229lbol.90oeqd.e85vmvg1jd0jo43nsljff","usage":"DEFAULT","_xmeta_modification_timestamp":"2019-07-19T00:09:17+0000","_xmeta_created_by_user":"isadmin","parameterName":"SupportedVariantsLibraries","_xmeta_repos_object_id":"c2e76d84.19e8ce7.jb96o1sfo.229kfle.nnoep1.8bb0ldj8bm1lp7shgno7nd","ParamType":"DIRECT"},{"_xmeta_optimistic_lock_id":"1","_xmeta_creation_timestamp":"2019-07-19T00:09:17+0000","valueExpression":"source","_xmeta_modified_by_user":"isadmin","_xmeta_lockingRoot":"c2e76d84.43058877.jb96o1sfo.229lbol.90oeqd.e85vmvg1jd0jo43nsljff","usage":"DEFAULT","_xmeta_modification_timestamp":"2019-07-19T00:09:17+0000","_xmeta_created_by_user":"isadmin","parameterName":"Context","_xmeta_repos_object_id":"c2e76d84.19e8ce7.jb96o1sfo.229nbl7.esh148.2cktq12atavo9hdpbl970t","ParamType":"DIRECT"},{"_xmeta_optimistic_lock_id":"1","_xmeta_creation_timestamp":"2019-07-19T00:09:17+0000","valueExpression":"0","_xmeta_modified_by_user":"isadmin","_xmeta_lockingRoot":"c2e76d84.43058877.jb96o1sfo.229lbol.90oeqd.e85vmvg1jd0jo43nsljff","usage":"DEFAULT","_xmeta_modification_timestamp":"2019-07-19T00:09:17+0000","_xmeta_created_by_user":"isadmin","parameterName":"RejectNumber","_xmeta_repos_object_id":"c2e76d84.19e8ce7.jb96o1sfo.229ired.23kl0u.4t06d7ek65srts9qc0dlrd","ParamType":"DIRECT"},{"_xmeta_optimistic_lock_id":"1","_xmeta_creation_timestamp":"2019-07-19T00:09:17+0000","valueExpression":"link","_xmeta_modified_by_user":"isadmin","_xmeta_lockingRoot":"c2e76d84.43058877.jb96o1sfo.229lbol.90oeqd.e85vmvg1jd0jo43nsljff","usage":"DEFAULT","_xmeta_modification_timestamp":"2019-07-19T00:09:17+0000","_xmeta_created_by_user":"isadmin","parameterName":"Orientation","_xmeta_repos_object_id":"c2e76d84.19e8ce7.jb96o1sfo.229l4gm.gukcrj.nlpe933efprlq7u98rm1fd","ParamType":"DIRECT"},{"_xmeta_optimistic_lock_id":"1","_xmeta_creation_timestamp":"2019-07-19T00:09:17+0000","valueExpression":"\/Connection\/Conductor","_xmeta_modified_by_user":"isadmin","_xmeta_lockingRoot":"c2e76d84.43058877.jb96o1sfo.229lbol.90oeqd.e85vmvg1jd0jo43nsljff","usage":"DEFAULT","_xmeta_modification_timestamp":"2019-07-19T00:09:17+0000","_xmeta_created_by_user":"isadmin","parameterName":"Conductor","_xmeta_repos_object_id":"c2e76d84.19e8ce7.jb96o1sfo.21p8j9b.8to9ov.s4cqqol8nvgv3rhj0rdpud","ParamType":"DIRECT"},{"_xmeta_optimistic_lock_id":"1","_xmeta_creation_timestamp":"2019-07-19T00:09:17+0000","valueExpression":"\/Connection\/Conductor\/Database","_xmeta_modified_by_user":"isadmin","_xmeta_lockingRoot":"c2e76d84.43058877.jb96o1sfo.229lbol.90oeqd.e85vmvg1jd0jo43nsljff","usage":"DEFAULT","_xmeta_modification_timestamp":"2019-07-19T00:09:17+0000","_xmeta_created_by_user":"isadmin","parameterName":"ConductorDatabase","_xmeta_repos_object_id":"c2e76d84.19e8ce7.jb96o1sfo.229fm9a.bed6o9.pup5la888j98ev34accetd","ParamType":"DIRECT"},{"_xmeta_optimistic_lock_id":"1","_xmeta_creation_timestamp":"2019-07-19T00:09:17+0000","valueExpression":"\/Connection\/Conductor\/DB2ClientLibFile","_xmeta_modified_by_user":"isadmin","_xmeta_lockingRoot":"c2e76d84.43058877.jb96o1sfo.229lbol.90oeqd.e85vmvg1jd0jo43nsljff","usage":"DEFAULT","_xmeta_modification_timestamp":"2019-07-19T00:09:17+0000","_xmeta_created_by_user":"isadmin","parameterName":"ConductorDB2ClientLibFile","_xmeta_repos_object_id":"c2e76d84.19e8ce7.jb96o1sfo.229imao.i01tls.kqk7dub03s0s7t1ruobmrd","ParamType":"DIRECT"},{"_xmeta_optimistic_lock_id":"1","_xmeta_creation_timestamp":"2019-07-19T00:09:17+0000","valueExpression":"false","_xmeta_modified_by_user":"isadmin","_xmeta_lockingRoot":"c2e76d84.43058877.jb96o1sfo.229lbol.90oeqd.e85vmvg1jd0jo43nsljff","usage":"DEFAULT","_xmeta_modification_timestamp":"2019-07-19T00:09:17+0000","_xmeta_created_by_user":"isadmin","parameterName":"RejectUsesPercentage","_xmeta_repos_object_id":"c2e76d84.19e8ce7.jb96o1sfo.21p3rch.gqtkmh.buffhhu9scoojq0j5bklid","ParamType":"DIRECT"},{"_xmeta_optimistic_lock_id":"1","_xmeta_creation_timestamp":"2019-07-19T00:09:17+0000","valueExpression":"-1","_xmeta_modified_by_user":"isadmin","_xmeta_lockingRoot":"c2e76d84.43058877.jb96o1sfo.229lbol.90oeqd.e85vmvg1jd0jo43nsljff","usage":"DEFAULT","_xmeta_modification_timestamp":"2019-07-19T00:09:17+0000","_xmeta_created_by_user":"isadmin","parameterName":"RejectFromLink","_xmeta_repos_object_id":"c2e76d84.19e8ce7.jb96o1sfo.229f17k.duoee6.kbtbrji2dal46nsgvkatdd","ParamType":"DIRECT"},{"_xmeta_optimistic_lock_id":"1","_xmeta_creation_timestamp":"2019-07-19T00:09:17+0000","valueExpression":"\/Connection\/Database","_xmeta_modified_by_user":"isadmin","_xmeta_lockingRoot":"c2e76d84.43058877.jb96o1sfo.229lbol.90oeqd.e85vmvg1jd0jo43nsljff","usage":"DEFAULT","_xmeta_modification_timestamp":"2019-07-19T00:09:17+0000","_xmeta_created_by_user":"isadmin","parameterName":"ConnectionString","_xmeta_repos_object_id":"c2e76d84.19e8ce7.jb96o1sfo.229hrmc.nn8hqc.ee5bhdl61kfnddjrjn8ibd","ParamType":"DIRECT"},{"_xmeta_optimistic_lock_id":"1","_xmeta_creation_timestamp":"2019-07-19T00:09:17+0000","valueExpression":"\/Connection\/Conductor\/Password","_xmeta_modified_by_user":"isadmin","_xmeta_lockingRoot":"c2e76d84.43058877.jb96o1sfo.229lbol.90oeqd.e85vmvg1jd0jo43nsljff","usage":"DEFAULT","_xmeta_modification_timestamp":"2019-07-19T00:09:17+0000","_xmeta_created_by_user":"isadmin","parameterName":"ConductorPassword","_xmeta_repos_object_id":"c2e76d84.19e8ce7.jb96o1sfo.229bjbh.7ctvs8.lm4a27oeekrp7el8b5n39d","ParamType":"DIRECT"},{"_xmeta_optimistic_lock_id":"1","_xmeta_creation_timestamp":"2019-07-19T00:09:17+0000","valueExpression":"\/Connection\/DB2ClientLibFile","_xmeta_modified_by_user":"isadmin","_xmeta_lockingRoot":"c2e76d84.43058877.jb96o1sfo.229lbol.90oeqd.e85vmvg1jd0jo43nsljff","usage":"DEFAULT","_xmeta_modification_timestamp":"2019-07-19T00:09:17+0000","_xmeta_created_by_user":"isadmin","parameterName":"DB2ClientLibFile","_xmeta_repos_object_id":"c2e76d84.19e8ce7.jb96o1sfo.229aun1.enj3jg.1evshia8qqsge9c20d3g9d","ParamType":"DIRECT"},{"_xmeta_optimistic_lock_id":"1","_xmeta_creation_timestamp":"2019-07-19T00:09:17+0000","valueExpression":"1.0","_xmeta_modified_by_user":"isadmin","_xmeta_lockingRoot":"c2e76d84.43058877.jb96o1sfo.229lbol.90oeqd.e85vmvg1jd0jo43nsljff","usage":"DEFAULT","_xmeta_modification_timestamp":"2019-07-19T00:09:17+0000","_xmeta_created_by_user":"isadmin","parameterName":"VariantVersion","_xmeta_repos_object_id":"c2e76d84.19e8ce7.jb96o1sfo.229fb21.8k2c26.33vs4htuip4tmun9drffdd","ParamType":"DIRECT"},{"_xmeta_optimistic_lock_id":"1","_xmeta_creation_timestamp":"2019-07-19T00:09:17+0000","valueExpression":"EE","_xmeta_modified_by_user":"isadmin","_xmeta_lockingRoot":"c2e76d84.43058877.jb96o1sfo.229lbol.90oeqd.e85vmvg1jd0jo43nsljff","usage":"DEFAULT","_xmeta_modification_timestamp":"2019-07-19T00:09:17+0000","_xmeta_created_by_user":"isadmin","parameterName":"Engine","_xmeta_repos_object_id":"c2e76d84.19e8ce7.jb96o1sfo.229c491.akv521.rqkvnorf0c3t69jb0drlpd","ParamType":"DIRECT"},{"_xmeta_optimistic_lock_id":"1","_xmeta_creation_timestamp":"2019-07-19T00:09:17+0000","valueExpression":"\/Connection\/Username","_xmeta_modified_by_user":"isadmin","_xmeta_lockingRoot":"c2e76d84.43058877.jb96o1sfo.229lbol.90oeqd.e85vmvg1jd0jo43nsljff","usage":"DEFAULT","_xmeta_modification_timestamp":"2019-07-19T00:09:17+0000","_xmeta_created_by_user":"isadmin","parameterName":"Username","_xmeta_repos_object_id":"c2e76d84.19e8ce7.jb96o1sfo.21p5nv2.8pg2fd.5vqk6g1en1aogrv3f7krqd","ParamType":"DIRECT"},{"_xmeta_optimistic_lock_id":"1","_xmeta_creation_timestamp":"2019-07-19T00:09:17+0000","valueExpression":"1.0","_xmeta_modified_by_user":"isadmin","_xmeta_lockingRoot":"c2e76d84.43058877.jb96o1sfo.229lbol.90oeqd.e85vmvg1jd0jo43nsljff","usage":"DEFAULT","_xmeta_modification_timestamp":"2019-07-19T00:09:17+0000","_xmeta_created_by_user":"isadmin","parameterName":"SupportedVariantsVersions","_xmeta_repos_object_id":"c2e76d84.19e8ce7.jb96o1sfo.229ih5r.aslm22.fb9a2so8ckp6348rkm5krd","ParamType":"DIRECT"},{"_xmeta_optimistic_lock_id":"1","_xmeta_creation_timestamp":"2019-07-19T00:09:17+0000","valueExpression":"ccdb2","_xmeta_modified_by_user":"isadmin","_xmeta_lockingRoot":"c2e76d84.43058877.jb96o1sfo.229lbol.90oeqd.e85vmvg1jd0jo43nsljff","usage":"DEFAULT","_xmeta_modification_timestamp":"2019-07-19T00:09:17+0000","_xmeta_created_by_user":"isadmin","parameterName":"VariantLibrary","_xmeta_repos_object_id":"c2e76d84.19e8ce7.jb96o1sfo.21p7gsm.lrca7n.8aaa3ta6bbvlkooacri2ed","ParamType":"DIRECT"},{"_xmeta_optimistic_lock_id":"1","_xmeta_creation_timestamp":"2019-07-19T00:09:17+0000","valueExpression":"V1;9.1::ccdb2","_xmeta_modified_by_user":"isadmin","_xmeta_lockingRoot":"c2e76d84.43058877.jb96o1sfo.229lbol.90oeqd.e85vmvg1jd0jo43nsljff","usage":"DEFAULT","_xmeta_modification_timestamp":"2019-07-19T00:09:17+0000","_xmeta_created_by_user":"isadmin","parameterName":"SupportedVariants","_xmeta_repos_object_id":"c2e76d84.19e8ce7.jb96o1sfo.229e99d.svcf38.f9gu3od28v0ctleseocbld","ParamType":"DIRECT"},{"_xmeta_optimistic_lock_id":"1","_xmeta_creation_timestamp":"2019-07-19T00:09:17+0000","valueExpression":"\/Connection\/Password","_xmeta_modified_by_user":"isadmin","_xmeta_lockingRoot":"c2e76d84.43058877.jb96o1sfo.229lbol.90oeqd.e85vmvg1jd0jo43nsljff","usage":"DEFAULT","_xmeta_modification_timestamp":"2019-07-19T00:09:17+0000","_xmeta_created_by_user":"isadmin","parameterName":"Password","_xmeta_repos_object_id":"c2e76d84.19e8ce7.jb96o1sfo.229j6md.t20fn4.os1neklomi85d343id4g7d","ParamType":"DIRECT"},{"_xmeta_optimistic_lock_id":"1","_xmeta_creation_timestamp":"2019-07-19T00:09:17+0000","valueExpression":"9.1","_xmeta_modified_by_user":"isadmin","_xmeta_lockingRoot":"c2e76d84.43058877.jb96o1sfo.229lbol.90oeqd.e85vmvg1jd0jo43nsljff","usage":"DEFAULT","_xmeta_modification_timestamp":"2019-07-19T00:09:17+0000","_xmeta_created_by_user":"isadmin","parameterName":"VariantName","_xmeta_repos_object_id":"c2e76d84.19e8ce7.jb96o1sfo.229enjt.h4tagi.4p6glrpfcpvk97at3f56dd","ParamType":"DIRECT"},{"_xmeta_optimistic_lock_id":"1","_xmeta_creation_timestamp":"2019-07-19T00:09:17+0000","valueExpression":"0","_xmeta_modified_by_user":"isadmin","_xmeta_lockingRoot":"c2e76d84.43058877.jb96o1sfo.229lbol.90oeqd.e85vmvg1jd0jo43nsljff","usage":"DEFAULT","_xmeta_modification_timestamp":"2019-07-19T00:09:17+0000","_xmeta_created_by_user":"isadmin","parameterName":"RejectThreshold","_xmeta_repos_object_id":"c2e76d84.19e8ce7.jb96o1sfo.21p8trc.0n1ed1.o950c0ue0go13pfp6ilvud","ParamType":"DIRECT"},{"_xmeta_optimistic_lock_id":"1","_xmeta_creation_timestamp":"2019-07-19T00:09:17+0000","valueExpression":"DB2Connector","_xmeta_modified_by_user":"isadmin","_xmeta_lockingRoot":"c2e76d84.43058877.jb96o1sfo.229lbol.90oeqd.e85vmvg1jd0jo43nsljff","usage":"DEFAULT","_xmeta_modification_timestamp":"2019-07-19T00:09:17+0000","_xmeta_created_by_user":"isadmin","parameterName":"ConnectorName","_xmeta_repos_object_id":"c2e76d84.19e8ce7.jb96o1sfo.21p5svq.aouv19.q7q8rvndbgr4jgj3raqg6d","ParamType":"DIRECT"},{"_xmeta_optimistic_lock_id":"2","_xmeta_creation_timestamp":"2019-07-19T00:09:17+0000","valueExpression":{"Usage":[{"valueExpression":"false","ATTR_type":"bool","parameterName":"MigratedJob"},{"valueExpression":"true","ATTR_modified":"true","ATTR_type":"bool","parameterName":"GenerateSQL"},{"valueExpression":"false","ATTR_type":"bool","parameterName":"EnableQuotedIDs"},{"valueExpression":"T","ATTR_modified":"true","ATTR_type":"string","parameterName":"TableName"},{"valueExpression":"false","ATTR_type":"bool","parameterName":"XMLColumnAsLOB"},{"valueExpression":"EXPR","ATTR_type":"string","parameterName":"PrefixForExpressionColumns"},{"parameterName":"SQL","Property":[{"valueExpression":"false","ATTR_collapsed":"true","ATTR_type":"bool","parameterName":"EnablePartitioning"}]},{"parameterName":"Transaction","Property":[{"valueExpression":"2000","ATTR_type":"int","parameterName":"RecordCount"},{"valueExpression":"0","ATTR_collapsed":"true","ATTR_type":"int","parameterName":"EndOfWave"}]},{"parameterName":"Session","Property":[{"valueExpression":"1","ATTR_type":"int","parameterName":"IsolationLevel"},{"valueExpression":"0","ATTR_type":"int","parameterName":"AutocommitMode"},{"valueExpression":"2000","ATTR_type":"int","parameterName":"ArraySize"},{"parameterName":"SchemaReconciliation","Property":[{"valueExpression":"true","ATTR_type":"bool","parameterName":"FailOnSizeMismatch"},{"valueExpression":"true","ATTR_type":"bool","parameterName":"FailOnTypeMismatch"},{"valueExpression":"false","ATTR_type":"bool","parameterName":"FailOnCodePageMismatch"}]},{"valueExpression":"false","ATTR_collapsed":"true","ATTR_type":"bool","parameterName":"PassLobLocator"}]},{"valueExpression":"false","ATTR_collapsed":"true","ATTR_type":"bool","parameterName":"BeforeAfter"},{"valueExpression":"2","ATTR_type":"int","parameterName":"ReOptimization"},{"valueExpression":"1","ATTR_collapsed":"true","ATTR_type":"int","parameterName":"LockWaitMode"},{"valueExpression":"false","ATTR_collapsed":"true","ATTR_type":"bool","parameterName":"LimitRows"}],"Connection":[{"valueExpression":"SAM115","ATTR_modified":"true","ATTR_type":"string","parameterName":"Database"},{"valueExpression":"db2inst1","ATTR_modified":"true","ATTR_type":"string","parameterName":"Username"},{"valueExpression":"{iisenc}L7EnXX9IztCtsNar+dS+Aw==","ATTR_modified":"true","ATTR_type":"protectedstring","parameterName":"Password"},{"valueExpression":"false","ATTR_collapsed":"true","ATTR_type":"bool","parameterName":"Conductor"},{"valueExpression":"false","ATTR_type":"bool","parameterName":"UseDirectConnections"},{"valueExpression":"true","ATTR_type":"bool","parameterName":"KeepConductorConnectionAlive"}],"Common":{"Context":"1","Variant":"9.1","DescriptorVersion":"1.0","PartitionType":"-1","RCP":"0"}},"_xmeta_modified_by_user":"isadmin","_xmeta_lockingRoot":"c2e76d84.43058877.jb96o1sfo.229lbol.90oeqd.e85vmvg1jd0jo43nsljff","usage":"DEFAULT","_xmeta_modification_timestamp":"2019-07-19T00:09:18+0000","_xmeta_created_by_user":"isadmin","parameterName":"XMLProperties","_xmeta_repos_object_id":"c2e76d84.19e8ce7.jb96o1sfo.229hmk9.9hctr1.8m2hv6jah6sjtcbh9eggbd","ParamType":"DIRECT"}],"_xmeta_created_by_user":"isadmin","OutputPins":"V0S0P1","NextRecordID":"0","StageTypeIsActive":"false"},{"_xmeta_optimistic_lock_id":"2","DSInputPin":[{"_xmeta_optimistic_lock_id":"1","_xmeta_creation_timestamp":"2019-07-19T00:09:17+0000","InternalID":"V0S3P1","_xmeta_modified_by_user":"isadmin","_xmeta_lockingRoot":"c2e76d84.43058877.jb96o1sfo.229lbol.90oeqd.e85vmvg1jd0jo43nsljff","_xmeta_repos_object_id":"c2e76d84.159ac31a.jb96o1sfo.229kqt5.ci1f13.3muksq9dtr3rjphj7vjaf","DSMetaBag":{"_xmeta_optimistic_lock_id":"2","Names":"RTColumnProp\u00a0Schema","_xmeta_creation_timestamp":"2019-07-19T00:09:17+0000","_xmeta_modified_by_user":"isadmin","_xmeta_lockingRoot":"c2e76d84.43058877.jb96o1sfo.229lbol.90oeqd.e85vmvg1jd0jo43nsljff","_xmeta_modification_timestamp":"2019-07-19T00:09:18+0000","Values":"0\u00a0record\r\n(\r\n  COL1:int32;\r\n)","_xmeta_created_by_user":"isadmin","_xmeta_repos_object_id":"c2e76d84.ac581434.jb96o1sfo.2299ui3.vfmpol.1515c4p0jcuiclt9o7kl1","Conditions":"\u00a0","Owners":"APT\u00a0APT"},"isTargetOf_Link":"c2e76d84.78bf4d29.jb96o1sfo.229bdl1.43gu86.79tugavfgp3gcus9je1d9","_xmeta_modification_timestamp":"2019-07-19T00:09:17+0000","PinType":"TrxInput","_xmeta_created_by_user":"isadmin","LinkType":"1","Partner":"V0S0|V0S0P1"}],"StageTypeClassName":"TransformerStage","_xmeta_creation_timestamp":"2019-07-19T00:09:17+0000","InternalID":"V0S3","_xmeta_modified_by_user":"isadmin","InputPins":"V0S3P1","_xmeta_lockingRoot":"c2e76d84.43058877.jb96o1sfo.229lbol.90oeqd.e85vmvg1jd0jo43nsljff","DSOutputPin":[{"_xmeta_optimistic_lock_id":"1","LeftTextPos":"457","_xmeta_creation_timestamp":"2019-07-19T00:09:17+0000","InternalID":"V0S3P2","_xmeta_modified_by_user":"isadmin","_xmeta_lockingRoot":"c2e76d84.43058877.jb96o1sfo.229lbol.90oeqd.e85vmvg1jd0jo43nsljff","_xmeta_repos_object_id":"c2e76d84.b9af3d05.jb96o1sfo.229b5d3.srdpgd.mn2epm7csnuv2b3ntiem9","TopTextPos":"239","DSMetaBag":{"_xmeta_optimistic_lock_id":"2","Names":"DiskWriteInc\u00a0BufFreeRun\u00a0MaxMemBufSize\u00a0QueueUpperSize\u00a0Schema","_xmeta_creation_timestamp":"2019-07-19T00:09:17+0000","_xmeta_modified_by_user":"isadmin","_xmeta_lockingRoot":"c2e76d84.43058877.jb96o1sfo.229lbol.90oeqd.e85vmvg1jd0jo43nsljff","_xmeta_modification_timestamp":"2019-07-19T00:09:18+0000","Values":"1048576\u00a050\u00a03145728\u00a00\u00a0record\r\n(\r\n  COL1:int32;\r\n)","_xmeta_created_by_user":"isadmin","_xmeta_repos_object_id":"c2e76d84.ac581434.jb96o1sfo.229cir2.mblo5m.n4f2gdpqcugtafn0r0nk5","Conditions":"\u00a0\u00a0\u00a0\u00a0","Owners":"APT\u00a0APT\u00a0APT\u00a0APT\u00a0APT"},"_xmeta_modification_timestamp":"2019-07-19T00:09:17+0000","PinType":"TrxOutput","_xmeta_created_by_user":"isadmin","Partner":"V0S6|V0S6P1","isSourceOf_Link":"c2e76d84.78bf4d29.jb96o1sfo.21p6gt4.8go02d.h90paosthfq38ge81u076"}],"_xmeta_repos_object_id":"c2e76d84.9f91cbaf.jb96o1sfo.229mcjf.d7vp3h.9n5bomv134793gk1tsmk0","DSMetaBag":{"_xmeta_optimistic_lock_id":"1","Names":"TrxGenCode\u00a0TrxGenCache\u00a0TrxClassName","_xmeta_creation_timestamp":"2019-07-19T00:09:18+0000","_xmeta_modified_by_user":"isadmin","_xmeta_lockingRoot":"c2e76d84.43058877.jb96o1sfo.229lbol.90oeqd.e85vmvg1jd0jo43nsljff","_xmeta_modification_timestamp":"2019-07-19T00:09:18+0000","Values":"\/\/\r\n\/\/ Generated file to implement the  transform operator.\r\n\/\/\r\n\r\n\/\/ define our input\/output link names\r\ninputname 0 DSLink2;\r\noutputname 0 DSLink5;\r\n\r\ninitialize {\r\n \/\/ define our control variables\r\n int8 RowRejected0;\r\n int8 NullSetVar0;\r\n\r\n}\r\n\r\nmainloop {\r\n\r\n \/\/ initialise the rejected row variable\r\n RowRejected0 = 1;\r\n\r\n \/\/ evaluate columns (no constraints) for link: DSLink5\r\n DSLink5.COL1 = (DSLink2.COL1 + 20);\r\n writerecord 0;\r\n RowRejected0 = 0;\r\n}\r\n\r\nfinish {\r\n}\r\n\u00a00\u00a0V0S3_T_Lineage_Transformer_3","_xmeta_created_by_user":"isadmin","_xmeta_repos_object_id":"c2e76d84.ac581434.jb96o1sfo.neji9mp.dgksko.nef16t6lu89509kigs7u8","Conditions":"\u00a0\u00a0","Owners":"APT\u00a0APT\u00a0APT"},"NextID":"3","isSystem":"false","StageType":"CTransformerStage","_xmeta_modification_timestamp":"2019-07-19T00:09:18+0000","name":"Transformer_3","DSParameterVal":[{"_xmeta_optimistic_lock_id":"1","_xmeta_creation_timestamp":"2019-07-19T00:09:17+0000","valueExpression":"0","_xmeta_modified_by_user":"isadmin","_xmeta_lockingRoot":"c2e76d84.43058877.jb96o1sfo.229lbol.90oeqd.e85vmvg1jd0jo43nsljff","usage":"DEFAULT","_xmeta_modification_timestamp":"2019-07-19T00:09:17+0000","_xmeta_created_by_user":"isadmin","parameterName":"ValidationStatus","_xmeta_repos_object_id":"c2e76d84.19e8ce7.jb96o1sfo.229ajnm.s2q5fl.7qa7jljegmifn6rsuta1hd","ParamType":"DIRECT"},{"_xmeta_optimistic_lock_id":"1","_xmeta_creation_timestamp":"2019-07-19T00:09:17+0000","valueExpression":"0","_xmeta_modified_by_user":"isadmin","_xmeta_lockingRoot":"c2e76d84.43058877.jb96o1sfo.229lbol.90oeqd.e85vmvg1jd0jo43nsljff","usage":"DEFAULT","_xmeta_modification_timestamp":"2019-07-19T00:09:17+0000","_xmeta_created_by_user":"isadmin","parameterName":"StageVarsMinimised","_xmeta_repos_object_id":"c2e76d84.19e8ce7.jb96o1sfo.21p2ig2.dcueao.58tsjk6gaqqjoa3126f32d","ParamType":"DIRECT"},{"_xmeta_optimistic_lock_id":"1","_xmeta_creation_timestamp":"2019-07-19T00:09:17+0000","valueExpression":"0","_xmeta_modified_by_user":"isadmin","_xmeta_lockingRoot":"c2e76d84.43058877.jb96o1sfo.229lbol.90oeqd.e85vmvg1jd0jo43nsljff","usage":"DEFAULT","_xmeta_modification_timestamp":"2019-07-19T00:09:17+0000","_xmeta_created_by_user":"isadmin","parameterName":"LoopVarsMaximised","_xmeta_repos_object_id":"c2e76d84.19e8ce7.jb96o1sfo.21p95rh.lluoqr.p5rgvl6u30emgrs2hhqo1d","ParamType":"DIRECT"},{"_xmeta_optimistic_lock_id":"1","_xmeta_creation_timestamp":"2019-07-19T00:09:17+0000","valueExpression":"0","_xmeta_modified_by_user":"isadmin","_xmeta_lockingRoot":"c2e76d84.43058877.jb96o1sfo.229lbol.90oeqd.e85vmvg1jd0jo43nsljff","usage":"DEFAULT","_xmeta_modification_timestamp":"2019-07-19T00:09:17+0000","_xmeta_created_by_user":"isadmin","parameterName":"BlockSize","_xmeta_repos_object_id":"c2e76d84.19e8ce7.jb96o1sfo.21p7bpv.cdsm56.ka5tm2qu5hr7fv38l4r0ed","ParamType":"DIRECT"},{"_xmeta_optimistic_lock_id":"1","_xmeta_creation_timestamp":"2019-07-19T00:09:17+0000","valueExpression":"0","_xmeta_modified_by_user":"isadmin","_xmeta_lockingRoot":"c2e76d84.43058877.jb96o1sfo.229lbol.90oeqd.e85vmvg1jd0jo43nsljff","usage":"DEFAULT","_xmeta_modification_timestamp":"2019-07-19T00:09:17+0000","_xmeta_created_by_user":"isadmin","parameterName":"MaxLoopIterations","_xmeta_repos_object_id":"c2e76d84.19e8ce7.jb96o1sfo.229k0a5.c3niq0.1f2fgc6msva8gclunu58nd","ParamType":"DIRECT"}],"_xmeta_created_by_user":"isadmin","OutputPins":"V0S3P2","StageTypeIsActive":"true"},{"_xmeta_optimistic_lock_id":"2","DSInputPin":[{"_xmeta_optimistic_lock_id":"1","_xmeta_creation_timestamp":"2019-07-19T00:09:17+0000","InternalID":"V0S6P1","_xmeta_modified_by_user":"isadmin","TransactionSize":"0","_xmeta_lockingRoot":"c2e76d84.43058877.jb96o1sfo.229lbol.90oeqd.e85vmvg1jd0jo43nsljff","_xmeta_repos_object_id":"c2e76d84.159ac31a.jb96o1sfo.229i6m9.omj8uq.hsarsrnevovrtcj6f4l1b","DSMetaBag":{"_xmeta_optimistic_lock_id":"1","Names":"RTColumnProp","_xmeta_creation_timestamp":"2019-07-19T00:09:17+0000","_xmeta_modified_by_user":"isadmin","_xmeta_lockingRoot":"c2e76d84.43058877.jb96o1sfo.229lbol.90oeqd.e85vmvg1jd0jo43nsljff","_xmeta_modification_timestamp":"2019-07-19T00:09:17+0000","Values":"0","_xmeta_created_by_user":"isadmin","_xmeta_repos_object_id":"c2e76d84.ac581434.jb96o1sfo.229busn.vm8ei6.944kuhehcu2r9513jfump","Owners":"APT"},"ConditionNotMet":"fail","LookupFail":"fail","TXNBehaviour":"0","isTargetOf_Link":"c2e76d84.78bf4d29.jb96o1sfo.21p6gt4.8go02d.h90paosthfq38ge81u076","EnableTxGroup":"0","_xmeta_modification_timestamp":"2019-07-19T00:09:17+0000","PinType":"CustomInput","_xmeta_created_by_user":"isadmin","LinkType":"1","Partner":"V0S3|V0S3P2"}],"StageTypeClassName":"CustomStage","_xmeta_creation_timestamp":"2019-07-19T00:09:17+0000","InternalID":"V0S6","_xmeta_modified_by_user":"isadmin","InputPins":"V0S6P1","_xmeta_lockingRoot":"c2e76d84.43058877.jb96o1sfo.229lbol.90oeqd.e85vmvg1jd0jo43nsljff","_xmeta_repos_object_id":"c2e76d84.9f91cbaf.jb96o1sfo.229gk7q.2l6c9j.tpr14t7o8kslbasvubj53","NextID":"2","AllowColumnMapping":"false","isSystem":"false","StageType":"DB2ConnectorPX","_xmeta_modification_timestamp":"2019-07-19T00:09:18+0000","name":"SAM_T","DSParameterVal":[{"_xmeta_optimistic_lock_id":"1","_xmeta_creation_timestamp":"2019-07-19T00:09:17+0000","valueExpression":"\/Connection\/Conductor\/Username","_xmeta_modified_by_user":"isadmin","_xmeta_lockingRoot":"c2e76d84.43058877.jb96o1sfo.229lbol.90oeqd.e85vmvg1jd0jo43nsljff","usage":"DEFAULT","_xmeta_modification_timestamp":"2019-07-19T00:09:17+0000","_xmeta_created_by_user":"isadmin","parameterName":"ConductorUsername","_xmeta_repos_object_id":"c2e76d84.19e8ce7.jb96o1sfo.229ln6r.th5tjr.qorvrf9q8oqo0ookt11avd","ParamType":"DIRECT"},{"_xmeta_optimistic_lock_id":"1","_xmeta_creation_timestamp":"2019-07-19T00:09:17+0000","valueExpression":"\/Connection\/Conductor\/Instance","_xmeta_modified_by_user":"isadmin","_xmeta_lockingRoot":"c2e76d84.43058877.jb96o1sfo.229lbol.90oeqd.e85vmvg1jd0jo43nsljff","usage":"DEFAULT","_xmeta_modification_timestamp":"2019-07-19T00:09:17+0000","_xmeta_created_by_user":"isadmin","parameterName":"ConductorInstance","_xmeta_repos_object_id":"c2e76d84.19e8ce7.jb96o1sfo.229bpki.9gpput.cg3sm23ptnnbk2r41t74pd","ParamType":"DIRECT"},{"_xmeta_optimistic_lock_id":"1","_xmeta_creation_timestamp":"2019-07-19T00:09:17+0000","valueExpression":"\/Connection\/Instance","_xmeta_modified_by_user":"isadmin","_xmeta_lockingRoot":"c2e76d84.43058877.jb96o1sfo.229lbol.90oeqd.e85vmvg1jd0jo43nsljff","usage":"DEFAULT","_xmeta_modification_timestamp":"2019-07-19T00:09:17+0000","_xmeta_created_by_user":"isadmin","parameterName":"Instance","_xmeta_repos_object_id":"c2e76d84.19e8ce7.jb96o1sfo.21p70na.ed9m11.um045vhbeqjuird9kqc5md","ParamType":"DIRECT"},{"_xmeta_optimistic_lock_id":"1","_xmeta_creation_timestamp":"2019-07-19T00:09:17+0000","valueExpression":"ccdb2","_xmeta_modified_by_user":"isadmin","_xmeta_lockingRoot":"c2e76d84.43058877.jb96o1sfo.229lbol.90oeqd.e85vmvg1jd0jo43nsljff","usage":"DEFAULT","_xmeta_modification_timestamp":"2019-07-19T00:09:17+0000","_xmeta_created_by_user":"isadmin","parameterName":"SupportedVariantsLibraries","_xmeta_repos_object_id":"c2e76d84.19e8ce7.jb96o1sfo.229nlok.rp812l.eoaife9huvtqk96fs2aagt","ParamType":"DIRECT"},{"_xmeta_optimistic_lock_id":"1","_xmeta_creation_timestamp":"2019-07-19T00:09:17+0000","valueExpression":"target","_xmeta_modified_by_user":"isadmin","_xmeta_lockingRoot":"c2e76d84.43058877.jb96o1sfo.229lbol.90oeqd.e85vmvg1jd0jo43nsljff","usage":"DEFAULT","_xmeta_modification_timestamp":"2019-07-19T00:09:17+0000","_xmeta_created_by_user":"isadmin","parameterName":"Context","_xmeta_repos_object_id":"c2e76d84.19e8ce7.jb96o1sfo.21p61vl.ckas3g.5348f4fbb45o2ne5jr166d","ParamType":"DIRECT"},{"_xmeta_optimistic_lock_id":"1","_xmeta_creation_timestamp":"2019-07-19T00:09:17+0000","valueExpression":"0","_xmeta_modified_by_user":"isadmin","_xmeta_lockingRoot":"c2e76d84.43058877.jb96o1sfo.229lbol.90oeqd.e85vmvg1jd0jo43nsljff","usage":"DEFAULT","_xmeta_modification_timestamp":"2019-07-19T00:09:17+0000","_xmeta_created_by_user":"isadmin","parameterName":"RejectNumber","_xmeta_repos_object_id":"c2e76d84.19e8ce7.jb96o1sfo.21p8e6q.9cgeun.hlfqq48kn43kaokpvp5uud","ParamType":"DIRECT"},{"_xmeta_optimistic_lock_id":"1","_xmeta_creation_timestamp":"2019-07-19T00:09:17+0000","valueExpression":"link","_xmeta_modified_by_user":"isadmin","_xmeta_lockingRoot":"c2e76d84.43058877.jb96o1sfo.229lbol.90oeqd.e85vmvg1jd0jo43nsljff","usage":"DEFAULT","_xmeta_modification_timestamp":"2019-07-19T00:09:17+0000","_xmeta_created_by_user":"isadmin","parameterName":"Orientation","_xmeta_repos_object_id":"c2e76d84.19e8ce7.jb96o1sfo.229n461.vq6hls.3dcbevertrpj07aigk4p0t","ParamType":"DIRECT"},{"_xmeta_optimistic_lock_id":"1","_xmeta_creation_timestamp":"2019-07-19T00:09:17+0000","valueExpression":"\/Connection\/Conductor","_xmeta_modified_by_user":"isadmin","_xmeta_lockingRoot":"c2e76d84.43058877.jb96o1sfo.229lbol.90oeqd.e85vmvg1jd0jo43nsljff","usage":"DEFAULT","_xmeta_modification_timestamp":"2019-07-19T00:09:17+0000","_xmeta_created_by_user":"isadmin","parameterName":"Conductor","_xmeta_repos_object_id":"c2e76d84.19e8ce7.jb96o1sfo.21p5irt.bo4t71.5an0s6j35sgm4b1l14f1qd","ParamType":"DIRECT"},{"_xmeta_optimistic_lock_id":"1","_xmeta_creation_timestamp":"2019-07-19T00:09:17+0000","valueExpression":"\/Connection\/Conductor\/Database","_xmeta_modified_by_user":"isadmin","_xmeta_lockingRoot":"c2e76d84.43058877.jb96o1sfo.229lbol.90oeqd.e85vmvg1jd0jo43nsljff","usage":"DEFAULT","_xmeta_modification_timestamp":"2019-07-19T00:09:17+0000","_xmeta_created_by_user":"isadmin","parameterName":"ConductorDatabase","_xmeta_repos_object_id":"c2e76d84.19e8ce7.jb96o1sfo.21p6rnh.raevv6.j22dclagantmrar9fpgumd","ParamType":"DIRECT"},{"_xmeta_optimistic_lock_id":"1","_xmeta_creation_timestamp":"2019-07-19T00:09:17+0000","valueExpression":"\/Connection\/Conductor\/DB2ClientLibFile","_xmeta_modified_by_user":"isadmin","_xmeta_lockingRoot":"c2e76d84.43058877.jb96o1sfo.229lbol.90oeqd.e85vmvg1jd0jo43nsljff","usage":"DEFAULT","_xmeta_modification_timestamp":"2019-07-19T00:09:17+0000","_xmeta_created_by_user":"isadmin","parameterName":"ConductorDB2ClientLibFile","_xmeta_repos_object_id":"c2e76d84.19e8ce7.jb96o1sfo.229d2ai.g8ov5h.ag5vr34fll4o2j5r17jh5d","ParamType":"DIRECT"},{"_xmeta_optimistic_lock_id":"1","_xmeta_creation_timestamp":"2019-07-19T00:09:17+0000","valueExpression":"false","_xmeta_modified_by_user":"isadmin","_xmeta_lockingRoot":"c2e76d84.43058877.jb96o1sfo.229lbol.90oeqd.e85vmvg1jd0jo43nsljff","usage":"DEFAULT","_xmeta_modification_timestamp":"2019-07-19T00:09:17+0000","_xmeta_created_by_user":"isadmin","parameterName":"RejectUsesPercentage","_xmeta_repos_object_id":"c2e76d84.19e8ce7.jb96o1sfo.229o07e.tt1oa6.cuv0kklvigi645k38usvgt","ParamType":"DIRECT"},{"_xmeta_optimistic_lock_id":"1","_xmeta_creation_timestamp":"2019-07-19T00:09:17+0000","valueExpression":"-1","_xmeta_modified_by_user":"isadmin","_xmeta_lockingRoot":"c2e76d84.43058877.jb96o1sfo.229lbol.90oeqd.e85vmvg1jd0jo43nsljff","usage":"DEFAULT","_xmeta_modification_timestamp":"2019-07-19T00:09:17+0000","_xmeta_created_by_user":"isadmin","parameterName":"RejectFromLink","_xmeta_repos_object_id":"c2e76d84.19e8ce7.jb96o1sfo.21p75pf.vfgvs0.f7uvmar7bilqn53a4n57md","ParamType":"DIRECT"},{"_xmeta_optimistic_lock_id":"1","_xmeta_creation_timestamp":"2019-07-19T00:09:17+0000","valueExpression":"\/Connection\/Database","_xmeta_modified_by_user":"isadmin","_xmeta_lockingRoot":"c2e76d84.43058877.jb96o1sfo.229lbol.90oeqd.e85vmvg1jd0jo43nsljff","usage":"DEFAULT","_xmeta_modification_timestamp":"2019-07-19T00:09:17+0000","_xmeta_created_by_user":"isadmin","parameterName":"ConnectionString","_xmeta_repos_object_id":"c2e76d84.19e8ce7.jb96o1sfo.229friq.h0ttg1.8u81lblp54n5tss98u0ttd","ParamType":"DIRECT"},{"_xmeta_optimistic_lock_id":"1","_xmeta_creation_timestamp":"2019-07-19T00:09:17+0000","valueExpression":"\/Connection\/Conductor\/Password","_xmeta_modified_by_user":"isadmin","_xmeta_lockingRoot":"c2e76d84.43058877.jb96o1sfo.229lbol.90oeqd.e85vmvg1jd0jo43nsljff","usage":"DEFAULT","_xmeta_modification_timestamp":"2019-07-19T00:09:17+0000","_xmeta_created_by_user":"isadmin","parameterName":"ConductorPassword","_xmeta_repos_object_id":"c2e76d84.19e8ce7.jb96o1sfo.229aemb.bcl6db.iel836eid2uq0lq9qo1ahd","ParamType":"DIRECT"},{"_xmeta_optimistic_lock_id":"1","_xmeta_creation_timestamp":"2019-07-19T00:09:17+0000","valueExpression":"\/Connection\/DB2ClientLibFile","_xmeta_modified_by_user":"isadmin","_xmeta_lockingRoot":"c2e76d84.43058877.jb96o1sfo.229lbol.90oeqd.e85vmvg1jd0jo43nsljff","usage":"DEFAULT","_xmeta_modification_timestamp":"2019-07-19T00:09:17+0000","_xmeta_created_by_user":"isadmin","parameterName":"DB2ClientLibFile","_xmeta_repos_object_id":"c2e76d84.19e8ce7.jb96o1sfo.229cpbv.bi57ul.t80fdekt0iju7alc6p4u5d","ParamType":"DIRECT"},{"_xmeta_optimistic_lock_id":"1","_xmeta_creation_timestamp":"2019-07-19T00:09:17+0000","valueExpression":"1.0","_xmeta_modified_by_user":"isadmin","_xmeta_lockingRoot":"c2e76d84.43058877.jb96o1sfo.229lbol.90oeqd.e85vmvg1jd0jo43nsljff","usage":"DEFAULT","_xmeta_modification_timestamp":"2019-07-19T00:09:17+0000","_xmeta_created_by_user":"isadmin","parameterName":"VariantVersion","_xmeta_repos_object_id":"c2e76d84.19e8ce7.jb96o1sfo.229h6rf.r5mfv8.msm67il6k90rektr6m42jd","ParamType":"DIRECT"},{"_xmeta_optimistic_lock_id":"1","_xmeta_creation_timestamp":"2019-07-19T00:09:17+0000","valueExpression":"EE","_xmeta_modified_by_user":"isadmin","_xmeta_lockingRoot":"c2e76d84.43058877.jb96o1sfo.229lbol.90oeqd.e85vmvg1jd0jo43nsljff","usage":"DEFAULT","_xmeta_modification_timestamp":"2019-07-19T00:09:17+0000","_xmeta_created_by_user":"isadmin","parameterName":"Engine","_xmeta_repos_object_id":"c2e76d84.19e8ce7.jb96o1sfo.229mi4f.030on5.s2s1j0rgdjdivq59mc720t","ParamType":"DIRECT"},{"_xmeta_optimistic_lock_id":"1","_xmeta_creation_timestamp":"2019-07-19T00:09:17+0000","valueExpression":"\/Connection\/Username","_xmeta_modified_by_user":"isadmin","_xmeta_lockingRoot":"c2e76d84.43058877.jb96o1sfo.229lbol.90oeqd.e85vmvg1jd0jo43nsljff","usage":"DEFAULT","_xmeta_modification_timestamp":"2019-07-19T00:09:17+0000","_xmeta_created_by_user":"isadmin","parameterName":"Username","_xmeta_repos_object_id":"c2e76d84.19e8ce7.jb96o1sfo.229hci4.17j4m1.nhccnkip1q5sraq1b6ghjd","ParamType":"DIRECT"},{"_xmeta_optimistic_lock_id":"1","_xmeta_creation_timestamp":"2019-07-19T00:09:17+0000","valueExpression":"1.0","_xmeta_modified_by_user":"isadmin","_xmeta_lockingRoot":"c2e76d84.43058877.jb96o1sfo.229lbol.90oeqd.e85vmvg1jd0jo43nsljff","usage":"DEFAULT","_xmeta_modification_timestamp":"2019-07-19T00:09:17+0000","_xmeta_created_by_user":"isadmin","parameterName":"SupportedVariantsVersions","_xmeta_repos_object_id":"c2e76d84.19e8ce7.jb96o1sfo.21p56pt.er3893.ti2qp2m99nhoujkpem04qd","ParamType":"DIRECT"},{"_xmeta_optimistic_lock_id":"1","_xmeta_creation_timestamp":"2019-07-19T00:09:17+0000","valueExpression":"ccdb2","_xmeta_modified_by_user":"isadmin","_xmeta_lockingRoot":"c2e76d84.43058877.jb96o1sfo.229lbol.90oeqd.e85vmvg1jd0jo43nsljff","usage":"DEFAULT","_xmeta_modification_timestamp":"2019-07-19T00:09:17+0000","_xmeta_created_by_user":"isadmin","parameterName":"VariantLibrary","_xmeta_repos_object_id":"c2e76d84.19e8ce7.jb96o1sfo.229dfcc.k2c6l2.724q4j4664o0om1jgv30ld","ParamType":"DIRECT"},{"_xmeta_optimistic_lock_id":"1","_xmeta_creation_timestamp":"2019-07-19T00:09:17+0000","valueExpression":"V1;9.1::ccdb2","_xmeta_modified_by_user":"isadmin","_xmeta_lockingRoot":"c2e76d84.43058877.jb96o1sfo.229lbol.90oeqd.e85vmvg1jd0jo43nsljff","usage":"DEFAULT","_xmeta_modification_timestamp":"2019-07-19T00:09:17+0000","_xmeta_created_by_user":"isadmin","parameterName":"SupportedVariants","_xmeta_repos_object_id":"c2e76d84.19e8ce7.jb96o1sfo.229g6p3.nu0tcv.hvedr2hpofrqn8om4e6g3d","ParamType":"DIRECT"},{"_xmeta_optimistic_lock_id":"1","_xmeta_creation_timestamp":"2019-07-19T00:09:17+0000","valueExpression":"\/Connection\/Password","_xmeta_modified_by_user":"isadmin","_xmeta_lockingRoot":"c2e76d84.43058877.jb96o1sfo.229lbol.90oeqd.e85vmvg1jd0jo43nsljff","usage":"DEFAULT","_xmeta_modification_timestamp":"2019-07-19T00:09:17+0000","_xmeta_created_by_user":"isadmin","parameterName":"Password","_xmeta_repos_object_id":"c2e76d84.19e8ce7.jb96o1sfo.229gbtg.in9v4v.fv6onse34ruqhj4tkfp23d","ParamType":"DIRECT"},{"_xmeta_optimistic_lock_id":"1","_xmeta_creation_timestamp":"2019-07-19T00:09:17+0000","valueExpression":"9.1","_xmeta_modified_by_user":"isadmin","_xmeta_lockingRoot":"c2e76d84.43058877.jb96o1sfo.229lbol.90oeqd.e85vmvg1jd0jo43nsljff","usage":"DEFAULT","_xmeta_modification_timestamp":"2019-07-19T00:09:17+0000","_xmeta_created_by_user":"isadmin","parameterName":"VariantName","_xmeta_repos_object_id":"c2e76d84.19e8ce7.jb96o1sfo.229kaeb.rc3021.15b0shbpvqpe00b12pplnd","ParamType":"DIRECT"},{"_xmeta_optimistic_lock_id":"1","_xmeta_creation_timestamp":"2019-07-19T00:09:17+0000","valueExpression":"0","_xmeta_modified_by_user":"isadmin","_xmeta_lockingRoot":"c2e76d84.43058877.jb96o1sfo.229lbol.90oeqd.e85vmvg1jd0jo43nsljff","usage":"DEFAULT","_xmeta_modification_timestamp":"2019-07-19T00:09:17+0000","_xmeta_created_by_user":"isadmin","parameterName":"RejectThreshold","_xmeta_repos_object_id":"c2e76d84.19e8ce7.jb96o1sfo.21p4f6f.v3hfp0.spisjs17dj86r9vde452ad","ParamType":"DIRECT"},{"_xmeta_optimistic_lock_id":"1","_xmeta_creation_timestamp":"2019-07-19T00:09:17+0000","valueExpression":"DB2Connector","_xmeta_modified_by_user":"isadmin","_xmeta_lockingRoot":"c2e76d84.43058877.jb96o1sfo.229lbol.90oeqd.e85vmvg1jd0jo43nsljff","usage":"DEFAULT","_xmeta_modification_timestamp":"2019-07-19T00:09:17+0000","_xmeta_created_by_user":"isadmin","parameterName":"ConnectorName","_xmeta_repos_object_id":"c2e76d84.19e8ce7.jb96o1sfo.229gv7p.thfiqb.v1v1iiki4tgqoa0q45kcjd","ParamType":"DIRECT"},{"_xmeta_optimistic_lock_id":"2","_xmeta_creation_timestamp":"2019-07-19T00:09:17+0000","valueExpression":{"Usage":[{"valueExpression":"false","ATTR_type":"bool","parameterName":"MigratedJob"},{"valueExpression":"0","ATTR_type":"int","parameterName":"WriteMode"},{"valueExpression":"true","ATTR_modified":"true","ATTR_type":"bool","parameterName":"GenerateSQL"},{"valueExpression":"false","ATTR_type":"bool","parameterName":"EnableQuotedIDs"},{"valueExpression":"SAM_T","ATTR_modified":"true","ATTR_type":"string","parameterName":"TableName"},{"valueExpression":"false","ATTR_type":"bool","parameterName":"XMLColumnAsLOB"},{"valueExpression":"EXPR","ATTR_type":"string","parameterName":"PrefixForExpressionColumns"},{"parameterName":"SQL","Property":[{"valueExpression":"true","ATTR_type":"bool","parameterName":"DirectInsert"}]},{"valueExpression":"1","ATTR_modified":"true","ATTR_type":"int","parameterName":"TableAction","Property":[{"valueExpression":"true","ATTR_type":"bool","parameterName":"GenerateCreateStatement","Property":[{"valueExpression":"true","ATTR_type":"bool","parameterName":"FailOnError"}]},{"valueExpression":"true","ATTR_type":"bool","parameterName":"TableActionFirst"}]},{"parameterName":"Transaction","Property":[{"valueExpression":"2000","ATTR_type":"int","parameterName":"RecordCount"}]},{"parameterName":"Session","Property":[{"valueExpression":"1","ATTR_type":"int","parameterName":"IsolationLevel"},{"valueExpression":"0","ATTR_type":"int","parameterName":"AutocommitMode"},{"valueExpression":"2000","ATTR_type":"int","parameterName":"ArraySize"},{"parameterName":"SchemaReconciliation","Property":[{"valueExpression":"true","ATTR_type":"bool","parameterName":"FailOnSizeMismatch"},{"valueExpression":"true","ATTR_type":"bool","parameterName":"FailOnTypeMismatch"},{"valueExpression":"false","ATTR_type":"bool","parameterName":"FailOnCodePageMismatch"},{"valueExpression":"true","ATTR_type":"bool","parameterName":"DropUnmatchedFields"}]},{"valueExpression":"true","ATTR_type":"bool","parameterName":"FailOnRowErrorPX"},{"valueExpression":"0","ATTR_type":"int","parameterName":"InsertBuffering","Property":[{"valueExpression":"0","ATTR_type":"int","parameterName":"AtomicArrays"}]}]},{"parameterName":"Logging","Property":[{"valueExpression":"false","ATTR_collapsed":"true","ATTR_type":"bool","parameterName":"LogColumnValues"}]},{"valueExpression":"false","ATTR_collapsed":"true","ATTR_type":"bool","parameterName":"BeforeAfter"},{"valueExpression":"2","ATTR_type":"int","parameterName":"ReOptimization"},{"valueExpression":"1","ATTR_collapsed":"true","ATTR_type":"int","parameterName":"LockWaitMode"}],"Connection":[{"valueExpression":"SAMPLE","ATTR_modified":"true","ATTR_type":"string","parameterName":"Database"},{"valueExpression":"db2inst1","ATTR_modified":"true","ATTR_type":"string","parameterName":"Username"},{"valueExpression":"{iisenc}uzWEqV7vNOIBNYcTnwBtYg==","ATTR_modified":"true","ATTR_type":"protectedstring","parameterName":"Password"},{"valueExpression":"false","ATTR_collapsed":"true","ATTR_type":"bool","parameterName":"Conductor"},{"valueExpression":"false","ATTR_type":"bool","parameterName":"UseDirectConnections"},{"valueExpression":"true","ATTR_type":"bool","parameterName":"KeepConductorConnectionAlive"}],"Common":{"Context":"2","Variant":"9.1","DescriptorVersion":"1.0","PartitionType":"-1","RCP":"0"}},"_xmeta_modified_by_user":"isadmin","_xmeta_lockingRoot":"c2e76d84.43058877.jb96o1sfo.229lbol.90oeqd.e85vmvg1jd0jo43nsljff","usage":"DEFAULT","_xmeta_modification_timestamp":"2019-07-19T00:09:18+0000","_xmeta_created_by_user":"isadmin","parameterName":"XMLProperties","_xmeta_repos_object_id":"c2e76d84.19e8ce7.jb96o1sfo.229jbm1.le49lv.60hljdv7e26g8p47hdaa7d","ParamType":"DIRECT"}],"_xmeta_created_by_user":"isadmin","NextRecordID":"0","StageTypeIsActive":"false"}],"_xmeta_optimistic_lock_id":"2","InternalID":"ROOT","_xmeta_modified_by_user":"isadmin","Category":"\\\\Jobs","MFProcessMetaData":"0","Act2ActEnableRowBuffer":"false","RelStagesInJobStatus":"-1","jobType":"PARALLEL","MFProcessMetaDataXMLFileExchangeMethod":"0","Act2ActUseIPC":"false","JobReportFlag":"false","PgmCustomizationFlag":"false","DSMetaBag":{"_xmeta_optimistic_lock_id":"2","Names":"AdvancedRuntimeOptions\u00a0IdentList\u00a0ClientCodePage","_xmeta_creation_timestamp":"2019-07-19T00:09:17+0000","_xmeta_modified_by_user":"isadmin","_xmeta_lockingRoot":"c2e76d84.43058877.jb96o1sfo.229lbol.90oeqd.e85vmvg1jd0jo43nsljff","_xmeta_modification_timestamp":"2019-07-19T00:09:18+0000","Values":"#DSProjectARTOptions#\u00a0SAM115_T|Transformer_3|SAM_T\u00a01252","_xmeta_created_by_user":"isadmin","_xmeta_repos_object_id":"c2e76d84.ac581434.jb96o1sfo.229lhic.5nh4pl.duit6c4eqk5q0008o0agv","Conditions":"\u00a0\u00a0","Owners":"APT\u00a0APT\u00a0APT"},"Act2ActOverideDefaults":"false","NULLIndicatorPosition":"0","ValidationStatus":"0","RecordPerformanceResults":"0","CenturyBreakYear":"30"},"XMetaLinkPoint":[{"objectRid":"c2e76d84.a57e5f89.jb96o0on4.hdbad5c.rjp2f8.7ec5jpinvrsl0up1n4f5s","XMetaAttributeValue":[{"stringValue":"DB2ConnectorPX","attributeName":"name"},{"stringValue":"NYIIS117:Project3","attributeName":"DSNameSpace"}],"className":"DSStageType","XMetaReferenceToLinkPoint":[{"ownerClassName":"DSStage","ownerPackageNsUri":"http:\/\/\/1.5\/DataStageX.ecore","reordered":"false","ownerRid":"c2e76d84.9f91cbaf.jb96o1sfo.229gk7q.2l6c9j.tpr14t7o8kslbasvubj53","referenceName":"of_StageType"},{"ownerClassName":"DSStage","ownerPackageNsUri":"http:\/\/\/1.5\/DataStageX.ecore","reordered":"false","ownerRid":"c2e76d84.9f91cbaf.jb96o1sfo.21p4231.nue8ib.uicaluudmj2ged3g4ncbi","referenceName":"of_StageType"}],"packageNsUri":"http:\/\/\/1.5\/DataStageX.ecore"},{"objectRid":"c2e76d84.a57e5f89.jb96o0omk.6us42b6.1j9b6k.gi9rp2fh82f5p0uth2279","XMetaAttributeValue":[{"stringValue":"CTransformerStage","attributeName":"name"},{"stringValue":"NYIIS117:Project3","attributeName":"DSNameSpace"}],"className":"DSStageType","XMetaReferenceToLinkPoint":[{"ownerClassName":"DSStage","ownerPackageNsUri":"http:\/\/\/1.5\/DataStageX.ecore","reordered":"false","ownerRid":"c2e76d84.9f91cbaf.jb96o1sfo.229mcjf.d7vp3h.9n5bomv134793gk1tsmk0","referenceName":"of_StageType"}],"packageNsUri":"http:\/\/\/1.5\/DataStageX.ecore"}],"AssetDataDescriptor":{"seedObjectRids":"[c2e76d84.43058877.jb96o1sfo.229lbol.90oeqd.e85vmvg1jd0jo43nsljff]","linkPointRids":"[c2e76d84.a57e5f89.jb96o0on4.hdbad5c.rjp2f8.7ec5jpinvrsl0up1n4f5s, c2e76d84.a57e5f89.jb96o0omk.6us42b6.1j9b6k.gi9rp2fh82f5p0uth2279]","AssetDataDetail":[{"value":"UTF-8","key":"option:xmiEncoding"},{"value":"false","key":"option:exportRequiredContextAsStubs"},{"value":"default","key":"option:registeredClosureRules"},{"value":"false","key":"option:useExternalLinkPointFormat"},{"value":"5.3:0","key":"version:closure:http:\/\/\/5.3\/ASCLModel.ecore"},{"value":"1.5:3","key":"version:closure:http:\/\/\/1.5\/DataStageX.ecore"},{"value":"3:2","key":"version:package:http:\/\/\/com\/ibm\/xmeta\/shared\/model\/3\/XMetaImportExport.ecore"},{"value":"4:0","key":"version:package:http:\/\/\/4.0\/com\/ibm\/xmeta\/model\/XMetaLinkPointElements.ecore"},{"value":"5.3:2","key":"version:package:http:\/\/\/5.3\/ASCLModel.ecore"},{"value":"4:0","key":"version:package:http:\/\/\/com\/ibm\/xmeta\/model\/4.0\/XMetaBase.ecore"},{"value":"1.5:3","key":"version:package:http:\/\/\/1.5\/DataStageX.ecore"},{"value":"11.7.0.2SP1-SNAPSHOT","key":"version:xmeta"},{"value":"2.5","key":"version:export"}]}}}